{
    "settings": {
        "modelBasePath": "/public/assets/scene/",
        "scaleFactor": 3.5
    },
    "objects": [
        {
            "id": "wall-door-rotate",
            "instances": [
                {
                    "rotationY": 1.5707963267948966,
                    "x": 0,
                    "y": 0,
                    "z": -10
                },
                {
                    "rotationY": 3.141592653589793,
                    "x": 6,
                    "y": 6.109439669051669,
                    "z": 6
                }
            ]
        },
        {
            "id": "wall-door",
            "instances": [
                {
                    "rotationY": 0,
                    "scaleX": 1,
                    "scaleY": 1,
                    "scaleZ": 1,
                    "x": 11.482106647510609,
                    "y": 0,
                    "z": 13.572137911393146
                }
            ]
        },
        {
            "id": "wall",
            "instances": [
                {
                    "rotationY": 0,
                    "scaleX": 11.961069898360734,
                    "scaleY": 1,
                    "scaleZ": 1,
                    "x": -11.175174334418632,
                    "y": 0.022863469844068618,
                    "z": 13.560403624769137
                },
                {
                    "rotationX": 0,
                    "rotationY": 0,
                    "rotationZ": 0,
                    "scaleX": 4.590124878006476,
                    "scaleY": 1,
                    "scaleZ": 1.1216226425152174,
                    "x": 21.14271928226047,
                    "y": 0,
                    "z": 13.689171801204365
                },
                {
                    "rotationY": 1.5707963267948966,
                    "scaleX": 11.961069898360734,
                    "scaleY": 1,
                    "scaleZ": 1,
                    "x": 26.38515509709364,
                    "y": 0,
                    "z": -7.383712664303114
                },
                {
                    "rotationX": -3.141592653589793,
                    "rotationY": 0,
                    "rotationZ": -3.141592653589793,
                    "scaleX": 11.961069898360734,
                    "scaleY": 1,
                    "scaleZ": 1,
                    "x": 3.7558118421436966,
                    "y": 0,
                    "z": -29.54802591277675
                },
                {
                    "rotationX": 0,
                    "rotationY": -1.5707963267948966,
                    "rotationZ": 0,
                    "scaleX": 5.810050365075267,
                    "scaleY": 1,
                    "scaleZ": 1,
                    "x": -16.489902831733474,
                    "y": 0,
                    "z": -20.217082494338772
                },
                {
                    "rotationY": 1.5707963267948966,
                    "scaleX": 5.810050365075267,
                    "scaleY": 1,
                    "scaleZ": 1,
                    "x": -31.687178883204194,
                    "y": 0,
                    "z": 4.087040240107764
                },
                {
                    "rotationX": -3.141592653589793,
                    "rotationY": 0,
                    "rotationZ": -3.141592653589793,
                    "scaleX": 4.382055426280721,
                    "scaleY": 1,
                    "scaleZ": 1,
                    "x": -25.79295712891389,
                    "y": 0,
                    "z": -8.467426360151663
                },
                {
                    "rotationY": 1.5707963267948966,
                    "scaleX": 6.655447447397516,
                    "scaleY": 1,
                    "scaleZ": 1,
                    "x": -31.687178883204194,
                    "y": 0,
                    "z": 2.7604960595831454
                },
                {
                    "rotationX": 0,
                    "rotationY": -1.5707963267948966,
                    "rotationZ": 0,
                    "scaleX": 6.655447447397516,
                    "scaleY": 1,
                    "scaleZ": 1,
                    "x": -31.215463780975746,
                    "y": 0,
                    "z": 2.7604960595831454
                },
                {
                    "rotationX": 0,
                    "rotationY": 0,
                    "rotationZ": 3.139256930314,
                    "scaleX": 17.779381421224972,
                    "scaleY": 2.927952203762705,
                    "scaleZ": 1,
                    "x": -3.386975976360784,
                    "y": 13.688820605870303,
                    "z": 13.560403624769137
                },
                {
                    "rotationX": 0,
                    "rotationY": 1.5707963267948966,
                    "rotationZ": 3.139256930314,
                    "scaleX": 17.779381421224972,
                    "scaleY": 2.927952203762705,
                    "scaleZ": 1,
                    "x": 26.38354282194777,
                    "y": 13.688820605870303,
                    "z": -17.096574414545497
                },
                {
                    "rotationX": 3.141592653589793,
                    "rotationY": 0,
                    "rotationZ": -0.002335723275793134,
                    "scaleX": 19.653184445493256,
                    "scaleY": 2.927952203762705,
                    "scaleZ": 1,
                    "x": 1.956191159439559,
                    "y": 13.688820605870303,
                    "z": -29.583774358433928
                },
                {
                    "rotationX": 3.141592653589793,
                    "rotationY": -1.5707963267948966,
                    "rotationZ": -0.0023357232757934346,
                    "scaleX": 9.321004254520677,
                    "scaleY": 2.927952203762705,
                    "scaleZ": 1,
                    "x": -16.48674962666242,
                    "y": 13.698366162533798,
                    "z": -25.487796169653294
                },
                {
                    "rotationX": 3.141592653589793,
                    "rotationY": -1.5707963267948966,
                    "rotationZ": -0.0023357232757934346,
                    "scaleX": 9.321004254520677,
                    "scaleY": 2.927952203762705,
                    "scaleZ": 1,
                    "x": -31.12733994589624,
                    "y": 13.698366162533798,
                    "z": -2.3205887072823153
                },
                {
                    "rotationX": 3.141592653589793,
                    "rotationY": -1.5707963267948966,
                    "rotationZ": -0.0023357232757934346,
                    "scaleX": 16.003453741240783,
                    "scaleY": 2.927952203762705,
                    "scaleZ": 1,
                    "x": -31.12733994589624,
                    "y": 13.698366162533798,
                    "z": -2.3205887072823153
                },
                {
                    "rotationX": 1.570796326794897,
                    "rotationY": 8.942029595802742e-05,
                    "rotationZ": -1.5731320500706902,
                    "scaleX": 11.457746862397084,
                    "scaleY": 6.473619602685403,
                    "scaleZ": 0.33630959915971365,
                    "x": -35.01948701078524,
                    "y": 3.456497959421295,
                    "z": -25.487796169653294
                }
            ]
        },
        {
            "id": "wall-corner",
            "instances": [
                {
                    "rotationY": 0,
                    "scaleX": 1,
                    "scaleY": 1,
                    "scaleZ": 1,
                    "x": 26.37378633781567,
                    "y": 0,
                    "z": -29.586363387325115
                },
                {
                    "rotationX": 3.141592653589793,
                    "rotationY": -1.5707963267948966,
                    "rotationZ": 3.141592653589793,
                    "scaleX": 1,
                    "scaleY": 1,
                    "scaleZ": 1,
                    "x": -16.488995579093395,
                    "y": 0,
                    "z": -8.461286948542755
                }
            ]
        },
        {
            "id": "column",
            "instances": [
                {
                    "rotationX": 0,
                    "rotationY": 0,
                    "rotationZ": 0,
                    "scaleX": 1,
                    "scaleY": 1,
                    "scaleZ": 1,
                    "x": -13.844587285229828,
                    "y": 0,
                    "z": -6.83586312791758
                }
            ]
        },
        {
            "id": "fence-door",
            "instances": [
                {
                    "rotationX": 0,
                    "rotationY": 1.5707963267948966,
                    "rotationZ": 0,
                    "scaleX": 1,
                    "scaleY": 1,
                    "scaleZ": 1,
                    "x": -12.654377979355756,
                    "y": 3.779482091002481,
                    "z": -27.018561120841536
                },
                {
                    "rotationX": 0,
                    "rotationY": 1.5707963267948966,
                    "rotationZ": 0,
                    "scaleX": 1,
                    "scaleY": 1,
                    "scaleZ": 1,
                    "x": -12.661026897791306,
                    "y": 3.779482091002481,
                    "z": -23.688494194878093
                },
                {
                    "rotationX": 0,
                    "rotationY": 1.5707963267948966,
                    "rotationZ": 0,
                    "scaleX": 1,
                    "scaleY": 1,
                    "scaleZ": 1,
                    "x": -12.65216901306621,
                    "y": 3.779482091002481,
                    "z": -20.224549732474355
                },
                {
                    "rotationX": 0,
                    "rotationY": 1.5707963267948966,
                    "rotationZ": 0,
                    "scaleX": 1,
                    "scaleY": 1,
                    "scaleZ": 1,
                    "x": -12.648677589352788,
                    "y": 3.779482091002481,
                    "z": -16.74575672624485
                },
                {
                    "rotationX": 0,
                    "rotationY": 1.5707963267948966,
                    "rotationZ": 0,
                    "scaleX": 1,
                    "scaleY": 1,
                    "scaleZ": 1,
                    "x": -12.651470762059041,
                    "y": 3.779482091002481,
                    "z": -16.74575672624485
                },
                {
                    "rotationX": 0,
                    "rotationY": 1.5707963267948966,
                    "rotationZ": 0,
                    "scaleX": 1,
                    "scaleY": 1,
                    "scaleZ": 1,
                    "x": -12.630387859150067,
                    "y": 3.779482091002481,
                    "z": -10.227962696757485
                },
                {
                    "rotationX": 0,
                    "rotationY": 1.5707963267948966,
                    "rotationZ": 0,
                    "scaleX": 1,
                    "scaleY": 1,
                    "scaleZ": 1,
                    "x": -12.623031559048323,
                    "y": 3.779482091002481,
                    "z": -13.457162736114423
                },
                {
                    "rotationX": 0,
                    "rotationY": 1.5707963267948966,
                    "rotationZ": 0,
                    "scaleX": 1,
                    "scaleY": 1,
                    "scaleZ": 1,
                    "x": -12.630387859150067,
                    "y": 3.779482091002481,
                    "z": -10.231033863287534
                }
            ]
        },
        {
            "id": "shelf-bags",
            "instances": [
                {
                    "rotationX": 0,
                    "rotationY": 0,
                    "rotationZ": 0,
                    "scaleX": 1,
                    "scaleY": 1,
                    "scaleZ": 1,
                    "x": -5.599281931055982,
                    "y": 0,
                    "z": -4.699983336169632
                },
                {
                    "rotationX": 0,
                    "rotationY": 0,
                    "rotationZ": 0,
                    "scaleX": 1,
                    "scaleY": 1,
                    "scaleZ": 1,
                    "x": -2.8093544885419934,
                    "y": 0,
                    "z": -4.699983336169632
                },
                {
                    "rotationX": 0,
                    "rotationY": 0,
                    "rotationZ": 0,
                    "scaleX": 1,
                    "scaleY": 1,
                    "scaleZ": 1,
                    "x": -0.22717592903661998,
                    "y": 0,
                    "z": -4.699983336169632
                },
                {
                    "rotationX": 0,
                    "rotationY": 0,
                    "rotationZ": 0,
                    "scaleX": 1,
                    "scaleY": 1,
                    "scaleZ": 1,
                    "x": 2.1924597653438913,
                    "y": 0,
                    "z": -4.699983336169632
                },
                {
                    "rotationX": 0,
                    "rotationY": 0,
                    "rotationZ": 0,
                    "scaleX": 1,
                    "scaleY": 1,
                    "scaleZ": 1,
                    "x": 2.2427292541132458,
                    "y": 0,
                    "z": -9.989380457747394
                },
                {
                    "rotationX": 0,
                    "rotationY": 0,
                    "rotationZ": 0,
                    "scaleX": 1,
                    "scaleY": 1,
                    "scaleZ": 1,
                    "x": -0.25526006191310735,
                    "y": 0,
                    "z": -9.989380457747394
                },
                {
                    "rotationX": 0,
                    "rotationY": 0,
                    "rotationZ": 0,
                    "scaleX": 1,
                    "scaleY": 1,
                    "scaleZ": 1,
                    "x": -2.7126016741828742,
                    "y": 0,
                    "z": -9.989380457747394
                },
                {
                    "rotationX": 0,
                    "rotationY": 0,
                    "rotationZ": 0,
                    "scaleX": 1,
                    "scaleY": 1,
                    "scaleZ": 1,
                    "x": -5.464689540465129,
                    "y": 0,
                    "z": -9.989380457747394
                }
            ]
        },
        {
            "id": "shelf-boxes",
            "instances": [
                {
                    "rotationX": 0,
                    "rotationY": 0,
                    "rotationZ": 0,
                    "scaleX": 1,
                    "scaleY": 1,
                    "scaleZ": 1,
                    "x": 7.800671195138431,
                    "y": 0,
                    "z": -4.56384554194335
                },
                {
                    "rotationX": 0,
                    "rotationY": 0,
                    "rotationZ": 0,
                    "scaleX": 1,
                    "scaleY": 1,
                    "scaleZ": 1,
                    "x": 10.919604434296785,
                    "y": 0,
                    "z": -4.500490524161387
                },
                {
                    "rotationX": -3.141592653589793,
                    "rotationY": 1.5707963267948966,
                    "rotationZ": -3.141592653589793,
                    "scaleX": 1,
                    "scaleY": 1,
                    "scaleZ": 1,
                    "x": 25.34780405124828,
                    "y": -0.04606481601996015,
                    "z": 6.451532270065413
                },
                {
                    "rotationX": -3.141592653589793,
                    "rotationY": 1.5707963267948966,
                    "rotationZ": -3.141592653589793,
                    "scaleX": 1,
                    "scaleY": 1,
                    "scaleZ": 1,
                    "x": 25.367926441958367,
                    "y": -0.04606481601996015,
                    "z": 3.4369770242309157
                },
                {
                    "rotationX": -3.141592653589793,
                    "rotationY": 1.5707963267948966,
                    "rotationZ": -3.141592653589793,
                    "scaleX": 1,
                    "scaleY": 1,
                    "scaleZ": 1,
                    "x": 25.34058780617811,
                    "y": -0.04606481601996015,
                    "z": 0.500343801752873
                },
                {
                    "rotationX": -3.141592653589793,
                    "rotationY": 1.5707963267948966,
                    "rotationZ": -3.141592653589793,
                    "scaleX": 1,
                    "scaleY": 1,
                    "scaleZ": 1,
                    "x": 25.315698169349794,
                    "y": -0.04606481601996015,
                    "z": -2.4385264680760264
                }
            ]
        },
        {
            "id": "shelf-end",
            "instances": [
                {
                    "rotationX": 0,
                    "rotationY": 0,
                    "rotationZ": 0,
                    "scaleX": 1,
                    "scaleY": 1,
                    "scaleZ": 1,
                    "x": -2.616484643520709,
                    "y": 0,
                    "z": -27.027407642669367
                },
                {
                    "rotationX": 0,
                    "rotationY": 0,
                    "rotationZ": 0,
                    "scaleX": 1,
                    "scaleY": 1,
                    "scaleZ": 1,
                    "x": 0.8039457411074795,
                    "y": 0,
                    "z": -27.027407642669367
                },
                {
                    "rotationX": 0,
                    "rotationY": 0,
                    "rotationZ": 0,
                    "scaleX": 1,
                    "scaleY": 1,
                    "scaleZ": 1,
                    "x": 4.421042729358982,
                    "y": 0,
                    "z": -27.027407642669367
                },
                {
                    "rotationX": 0,
                    "rotationY": 0,
                    "rotationZ": 0,
                    "scaleX": 1,
                    "scaleY": 1,
                    "scaleZ": 1,
                    "x": 7.97162202904243,
                    "y": 0,
                    "z": -27.027407642669367
                },
                {
                    "rotationX": 0,
                    "rotationY": 0,
                    "rotationZ": 0,
                    "scaleX": 1,
                    "scaleY": 1,
                    "scaleZ": 1,
                    "x": 11.472431667129946,
                    "y": 0,
                    "z": -27.027407642669367
                }
            ]
        },
        {
            "id": "display-fruit",
            "instances": [
                {
                    "rotationX": 0,
                    "rotationY": 0,
                    "rotationZ": 0,
                    "scaleX": 0.595009763695517,
                    "scaleY": 0.595009763695517,
                    "scaleZ": 0.595009763695517,
                    "x": -13.168374923887121,
                    "y": 0,
                    "z": -4.9049118737161805
                },
                {
                    "x": 19.56783417640742,
                    "y": 0,
                    "z": 12.035246989390682,
                    "rotationX": 0,
                    "rotationY": 0,
                    "rotationZ": 0,
                    "scaleX": 0.44230300818799856,
                    "scaleY": 0.44230300818799856,
                    "scaleZ": 0.44230300818799856
                },
                {
                    "x": 20.209880148075136,
                    "y": 0.9016048864941506,
                    "z": 6.782870430190646,
                    "rotationX": 0,
                    "rotationY": 0,
                    "rotationZ": 0,
                    "scaleX": 0.33100357652173057,
                    "scaleY": 0.33100357652173057,
                    "scaleZ": 0.33100357652173057
                }
            ]
        },
        {
            "id": "display-bread",
            "instances": [
                {
                    "rotationX": 0,
                    "rotationY": 0,
                    "rotationZ": 0,
                    "scaleX": 1,
                    "scaleY": 1,
                    "scaleZ": 1,
                    "x": -18.13905750742864,
                    "y": -0.019464785476937863,
                    "z": -6.409532760125579
                }
            ]
        },
        {
            "id": "bottle-return",
            "instances": [
                {
                    "rotationX": -3.141592653589793,
                    "rotationY": 0,
                    "rotationZ": -3.141592653589793,
                    "scaleX": 1,
                    "scaleY": 1,
                    "scaleZ": 1,
                    "x": 7.983183038210595,
                    "y": 0,
                    "z": 11.994644367867652
                },
                {
                    "rotationX": -3.141592653589793,
                    "rotationY": 0,
                    "rotationZ": -3.141592653589793,
                    "scaleX": 1,
                    "scaleY": 1,
                    "scaleZ": 1,
                    "x": 5.493029356022345,
                    "y": 0,
                    "z": 11.994644367867652
                }
            ]
        },
        {
            "id": "shopping-cart",
            "instances": [
                {
                    "rotationX": 0,
                    "rotationY": 0,
                    "rotationZ": 0,
                    "scaleX": 1,
                    "scaleY": 1,
                    "scaleZ": 1,
                    "x": 15.286596014608314,
                    "y": 0,
                    "z": -0.6714102480946933
                }
            ]
        },
        {
            "id": "shopping-basket",
            "instances": [
                {
                    "rotationX": 0,
                    "rotationY": 0,
                    "rotationZ": 0,
                    "scaleX": 1,
                    "scaleY": 1,
                    "scaleZ": 1,
                    "x": 13.060193193574147,
                    "y": 0,
                    "z": -3.9591110959481837
                },
                {
                    "rotationX": 0,
                    "rotationY": 0,
                    "rotationZ": 0,
                    "scaleX": 1,
                    "scaleY": 1,
                    "scaleZ": 1,
                    "x": 20.362441246802923,
                    "y": 0.8594571922743433,
                    "z": -2.613215244969141
                },
                {
                    "x": 21.03127698578675,
                    "y": -0.009468640193373679,
                    "z": 11.655286162313741,
                    "rotationX": 0,
                    "rotationY": 0,
                    "rotationZ": 0,
                    "scaleX": 1,
                    "scaleY": 1,
                    "scaleZ": 1
                }
            ]
        },
        {
            "id": "cash-register",
            "instances": [
                {
                    "rotationX": 0,
                    "rotationY": 0,
                    "rotationZ": 0,
                    "scaleX": 1,
                    "scaleY": 1,
                    "scaleZ": 1,
                    "x": 21.142209053257087,
                    "y": 0.0497285055386385,
                    "z": -2.2990293761573426
                },
                {
                    "rotationX": 0,
                    "rotationY": 0,
                    "rotationZ": 0,
                    "scaleX": 1,
                    "scaleY": 1,
                    "scaleZ": 1,
                    "x": 21.11243734616894,
                    "y": 0.0497285055386385,
                    "z": 1.9910368936828675
                },
                {
                    "rotationX": 0,
                    "rotationY": 0,
                    "rotationZ": 0,
                    "scaleX": 1,
                    "scaleY": 1,
                    "scaleZ": 1,
                    "x": 21.089808520115298,
                    "y": 0.0497285055386385,
                    "z": 6.065167092438095
                },
                {
                    "rotationX": 0,
                    "rotationY": 0,
                    "rotationZ": 0,
                    "scaleX": 1,
                    "scaleY": 1,
                    "scaleZ": 1,
                    "x": 21.142209053257087,
                    "y": 0.0497285055386385,
                    "z": -2.2990293761573426
                }
            ]
        },
        {
            "id": "freezers-standing",
            "instances": [
                {
                    "x": 22.85909958146201,
                    "y": 0.05279317666299743,
                    "z": 9.917524576910694,
                    "rotationX": -3.141592653589793,
                    "rotationY": -0.5579798321866911,
                    "rotationZ": -3.141592653589793,
                    "scaleX": 1,
                    "scaleY": 1,
                    "scaleZ": 1
                }
            ]
        }
    ],
    "spawners": [
        {
            "active": true,
            "cooldown": 7000,
            "itemIds": [
                "turkey",
                "whole-ham",
                "meat-ribs",
                "meat-cooked",
                "meat-sausage"
            ],
            "position": {
                "x": -8,
                "y": 1,
                "z": -8
            },
            "quantities": [
                2,
                1,
                2,
                3,
                2
            ],
            "type": "item"
        },
        {
            "active": true,
            "cooldown": 6000,
            "itemIds": [
                "loaf-baguette",
                "loaf-round",
                "muffin",
                "pancakes",
                "waffle"
            ],
            "position": {
                "x": -8,
                "y": 1,
                "z": 0
            },
            "quantities": [
                3,
                2,
                4,
                2,
                2
            ],
            "type": "item"
        },
        {
            "active": true,
            "cooldown": 8000,
            "itemIds": [
                "pizza",
                "sandwich",
                "salad",
                "sub",
                "taco"
            ],
            "position": {
                "x": 8,
                "y": 1,
                "z": -8
            },
            "quantities": [
                1,
                2,
                2,
                1,
                2
            ],
            "type": "item"
        },
        {
            "active": true,
            "cooldown": 6000,
            "itemIds": [
                "sushi-salmon",
                "maki-roe",
                "maki-salmon",
                "mussel",
                "rice-ball"
            ],
            "position": {
                "x": 8,
                "y": 1,
                "z": 0
            },
            "quantities": [
                2,
                3,
                3,
                4,
                2
            ],
            "type": "item"
        },
        {
            "active": true,
            "cooldown": 5000,
            "itemIds": [
                "watermelon",
                "strawberry",
                "pineapple",
                "orange",
                "pear"
            ],
            "position": {
                "x": 0,
                "y": 1,
                "z": -8
            },
            "quantities": [
                1,
                4,
                2,
                3,
                3
            ],
            "type": "item"
        },
        {
            "active": true,
            "cooldown": 7000,
            "itemIds": [
                "ice-cream",
                "sundae",
                "pudding",
                "popsicle"
            ],
            "position": {
                "x": 0,
                "y": 1,
                "z": 4
            },
            "quantities": [
                2,
                1,
                2,
                3,
                2
            ],
            "type": "item"
        },
        {
            "active": true,
            "cooldown": 9000,
            "itemIds": [
                "wine-red",
                "wine-white",
                "soda-bottle",
                "soda-can",
                "soda-glass"
            ],
            "position": {
                "x": -4,
                "y": 1,
                "z": 4
            },
            "quantities": [
                1,
                1,
                2,
                3,
                2
            ],
            "type": "item"
        },
        {
            "active": true,
            "cooldown": 5000,
            "itemIds": [
                "carrot",
                "cup-coffee"
            ],
            "position": {
                "x": 4,
                "y": 1,
                "z": 4
            },
            "quantities": [
                3,
                4,
                3,
                2,
                4
            ],
            "type": "item"
        }
    ]
}